subscription/__init__.py
subscription/admin.py
subscription/apps.py
subscription/billing.py
subscription/error_handling.py
subscription/feature.py
subscription/manager.py
subscription/settings.py
subscription/migrations/0001_initial.py
subscription/migrations/__init__.py
subscription/models/__init__.py
subscription/models/error.py
subscription/models/feature.py
subscription/models/plan.py
subscription/models/wallet.py
django_enhanced_subscriptions-1.0.2.dist-info/METADATA
django_enhanced_subscriptions-1.0.2.dist-info/WHEEL
django_enhanced_subscriptions-1.0.2.dist-info/licenses/AUTHORS.rst
django_enhanced_subscriptions-1.0.2.dist-info/licenses/LICENCE
django_enhanced_subscriptions-1.0.2.dist-info/RECORD
