Metadata-Version: 2.3
Name: django-enhanced-subscriptions
Version: 1.0.2
Summary: This Django library provides a comprehensive solution for managing subscriptions, feature access and wallet functionality
Project-URL: Homepage, https://django-enhanced-subscriptions.readthedocs.io/en/latest/index.html
Author-email: Josephat Macharia <josemash4@gmail.com>
License: MIT
License-File: AUTHORS.rst
License-File: LICENCE
Classifier: Environment :: Web Environment
Classifier: Framework :: Django
Classifier: Framework :: Django :: 5.0
Classifier: Intended Audience :: Developers
Classifier: License :: OSI Approved :: MIT License
Classifier: Operating System :: OS Independent
Classifier: Programming Language :: Python
Classifier: Programming Language :: Python :: 3
Classifier: Programming Language :: Python :: 3.8
Classifier: Programming Language :: Python :: 3.9
Classifier: Programming Language :: Python :: 3.10
Classifier: Topic :: Internet :: WWW/HTTP
Requires-Python: >=3.8
Requires-Dist: django>=5.0.6
Provides-Extra: test
Requires-Dist: black; extra == 'test'
Requires-Dist: coverage; extra == 'test'
Requires-Dist: flake8; extra == 'test'
Requires-Dist: isort; extra == 'test'
Requires-Dist: model-bakery>=1.18.1; extra == 'test'
Requires-Dist: pytest-cov; extra == 'test'
Requires-Dist: pytest-django>=4.8.0; extra == 'test'
Requires-Dist: pytest>=8.2.1; extra == 'test'
Requires-Dist: tox; extra == 'test'
